{
  "sections": {
    "93ee7aec-bb9f-45b2-b98a-0a356ff43944": {
      "type": "no_space_img",
      "settings": {
        "sensorsName": "",
        "bg_image": "shopify:\/\/shop_images\/02_8b727ea9-cefc-492a-89aa-cc79c85b6fec.jpg",
        "web_bg_image": "shopify:\/\/shop_images\/02_11aa6f06-8d26-492e-bb8d-77581f9a30c0.jpg",
        "link": "",
        "shadow": false
      }
    },
    "main": {
      "type": "main-page",
      "disabled": true,
      "settings": {
      }
    },
    "newsletter": {
      "type": "newsletter",
      "disabled": true,
      "settings": {
        "title": "Newsletter",
        "content": "<p>A short sentence describing what someone will receive by subscribing<\/p>",
        "background": "#1e2d7d",
        "text": "#ffffff"
      }
    },
    "d436c85f-f4e6-4b3e-991f-0922651867b1": {
      "type": "offers",
      "disabled": true,
      "blocks": {
        "template--14882387525711__d436c85f-f4e6-4b3e-991f-0922651867b1-1666864435356fe776-0": {
          "type": "offer",
          "settings": {
            "title": "Method",
            "content": "<p>Standard Shipping<\/p>"
          }
        },
        "template--14882387525711__d436c85f-f4e6-4b3e-991f-0922651867b1-1666864435356fe776-1": {
          "type": "offer",
          "settings": {
            "title": "Shipping Time",
            "content": "<p>To US,UK,FR,DE,NZ: 11-21 Business Days<br\/>To Other Countries: 15-28 Business Days<\/p>"
          }
        },
        "ea54972d-f61f-442b-b664-d1ad9d9848e1": {
          "type": "offer",
          "settings": {
            "title": "Price",
            "content": "<p>$8.9<\/p>"
          }
        }
      },
      "block_order": [
        "template--14882387525711__d436c85f-f4e6-4b3e-991f-0922651867b1-1666864435356fe776-0",
        "template--14882387525711__d436c85f-f4e6-4b3e-991f-0922651867b1-1666864435356fe776-1",
        "ea54972d-f61f-442b-b664-d1ad9d9848e1"
      ],
      "settings": {
        "items_per_row": 3,
        "stack_mobile": false
      }
    },
    "4fc46bb4-55cd-4335-9ee7-6b32132e9ca6": {
      "type": "no_space_img",
      "settings": {
        "sensorsName": "",
        "bg_image": "shopify:\/\/shop_images\/03.jpg",
        "web_bg_image": "shopify:\/\/shop_images\/03_ebcc8698-aa14-4d6b-a89a-7c9ff5972887.jpg",
        "link": "",
        "shadow": false
      }
    },
    "912d9a55-ac02-4661-87c7-0a09ed904a50": {
      "type": "no_space_img",
      "settings": {
        "sensorsName": "",
        "bg_image": "shopify:\/\/shop_images\/04_67107d8d-eb4f-426c-bd37-6333f5567207.jpg",
        "web_bg_image": "shopify:\/\/shop_images\/04_230ac131-84c7-4a38-888c-3af2316d91b6.jpg",
        "link": "",
        "shadow": false
      }
    },
    "ac61df80-e05d-4014-b4c1-dd3eda55cedd": {
      "type": "no_space_img",
      "settings": {
        "sensorsName": "",
        "bg_image": "shopify:\/\/shop_images\/05.jpg",
        "web_bg_image": "shopify:\/\/shop_images\/05_28945740-9948-470d-86a1-cec24e8076ef.jpg",
        "link": "https:\/\/www.skamx.com\/",
        "shadow": false
      }
    },
    "65c872fe-04fc-4e26-b5fb-c71a7a967c56": {
      "type": "no_space_img",
      "settings": {
        "sensorsName": "",
        "bg_image": "shopify:\/\/shop_images\/06_5d1f08a5-6399-4b96-b8a9-b07d511aaa19.jpg",
        "web_bg_image": "shopify:\/\/shop_images\/06_bca8ea00-2813-421b-b2d7-32080a39eff0.jpg",
        "link": "",
        "shadow": false
      }
    },
    "b9be338c-a528-4236-a0d2-9e9c5a330f21": {
      "type": "no_space_img",
      "settings": {
        "sensorsName": "",
        "bg_image": "shopify:\/\/shop_images\/07_7f9aa715-1f6e-4232-a48e-c5a1971808b9.jpg",
        "web_bg_image": "shopify:\/\/shop_images\/07_06cf832f-4862-443b-a84f-79c8b0d8cb36.jpg",
        "link": "",
        "shadow": false
      }
    },
    "5303b234-8891-46b0-999d-11dd03890abf": {
      "type": "no_space_img",
      "settings": {
        "sensorsName": "",
        "bg_image": "shopify:\/\/shop_images\/08_41410bc1-e07d-4339-8929-92410e96f33d.jpg",
        "web_bg_image": "shopify:\/\/shop_images\/08_e18f22cd-369e-40a1-9e2f-1e23573db5ab.jpg",
        "link": "",
        "shadow": false
      }
    },
    "570e956b-a95f-4227-8b62-82b45f4e5e4f": {
      "type": "no_space_img",
      "settings": {
        "sensorsName": "",
        "bg_image": "shopify:\/\/shop_images\/09_93ac5f78-9d4b-415f-80d7-084c60973df1.jpg",
        "web_bg_image": "shopify:\/\/shop_images\/09_0811f09e-9189-459c-a420-85fccba55f2f.jpg",
        "link": "",
        "shadow": false
      }
    },
    "cf0ad295-0f1d-445f-9687-c6e08cc7d225": {
      "type": "featured-collection",
      "settings": {
        "collection": "new-in",
        "title": "YOU MAY ALSO LIKE",
        "section_title_layout": "left",
        "products_count": 12,
        "layout": "vertical",
        "stack_products": false,
        "show_quick_buy": false,
        "link_title": "View all",
        "link_url": "",
        "padding_top": 0,
        "padding_bottom": 0,
        "margin_top": 0,
        "margin_bottom": 0,
        "background": "linear-gradient(210deg, rgba(203, 68, 194, 1), rgba(255, 201, 104, 1), rgba(255, 255, 255, 1) 1%)"
      }
    }
  },
  "order": [
    "93ee7aec-bb9f-45b2-b98a-0a356ff43944",
    "main",
    "newsletter",
    "d436c85f-f4e6-4b3e-991f-0922651867b1",
    "4fc46bb4-55cd-4335-9ee7-6b32132e9ca6",
    "912d9a55-ac02-4661-87c7-0a09ed904a50",
    "ac61df80-e05d-4014-b4c1-dd3eda55cedd",
    "65c872fe-04fc-4e26-b5fb-c71a7a967c56",
    "b9be338c-a528-4236-a0d2-9e9c5a330f21",
    "5303b234-8891-46b0-999d-11dd03890abf",
    "570e956b-a95f-4227-8b62-82b45f4e5e4f",
    "cf0ad295-0f1d-445f-9687-c6e08cc7d225"
  ]
}
